mcp_server_monday_osvaldo/__init__.py
mcp_server_monday_osvaldo/board.py
mcp_server_monday_osvaldo/constants.py
mcp_server_monday_osvaldo/document.py
mcp_server_monday_osvaldo/item.py
mcp_server_monday_osvaldo/server.py
mcp_server_monday_osvaldo/tools.py
mcp_server_monday_osvaldo-0.2.9.dist-info/METADATA
mcp_server_monday_osvaldo-0.2.9.dist-info/WHEEL
mcp_server_monday_osvaldo-0.2.9.dist-info/entry_points.txt
mcp_server_monday_osvaldo-0.2.9.dist-info/licenses/LICENSE
mcp_server_monday_osvaldo-0.2.9.dist-info/RECORD
