Metadata-Version: 2.4
Name: mcp_server_monday_osvaldo
Version: 0.2.9
Summary: MCP Server for monday.com
Project-URL: Homepage, https://github.com/sakce/mcp-server-monday/
Author: Jovan Sakovic
License-File: LICENSE
Requires-Python: >=3.10
Requires-Dist: mcp[cli]>=1.2.1
Requires-Dist: monday>=2.0.1
Requires-Dist: requests>=2.32.3
Requires-Dist: ruff>=0.9.6
